Metadata-Version: 2.1
Name: odoo8-addon-mass-editing
Version: 8.0.1.3.0.99.dev41
Summary: Mass Editing
Home-page: http://www.serpentcs.com
Author: Serpent Consulting Services,Odoo Community Association (OCA)
Author-email: support@odoo-community.org
License: GPL-3 or any later version
Platform: UNKNOWN
Classifier: Programming Language :: Python
Classifier: Framework :: Odoo
Classifier: Framework :: Odoo :: 8.0
Classifier: License :: OSI Approved :: GNU General Public License v3 or later (GPLv3+)
Requires-Python: ~=2.7
Requires-Dist: odoo (<9.0a,>=8.0a)
